[
    "{\"type\": \"DAILY\", \"task\": \"Clean the floor\", \"start\": \"2024-01-01\", \"finish\": \"2025-01-01\", \"periodicity\": [], \"trackData\": [\"2024-02-17T09:17:09.652406\", \"2024-02-18T09:35:42.412585\", \"2024-02-19T09:35:55.241712\"], \"maxstreak\": 3}",
    "{\"type\": \"WEEKLY\", \"task\": \"Clean the windows\", \"start\": \"2024-01-01\", \"finish\": \"2025-01-01\", \"periodicity\": [\"MONDAY\", \"FRIDAY\", \"SUNDAY\"], \"trackData\": [\"2024-01-01T09:37:12.586725\", \"2024-01-05T09:38:33.645285\", \"2024-01-07T09:38:46.536181\"], \"maxstreak\": 3}",
    "{\"type\": \"MONTHLY\", \"task\": \"Clean the car\", \"start\": \"2024-01-01\", \"finish\": \"2025-01-01\", \"periodicity\": [2, 5, 18], \"trackData\": [\"2024-01-02T09:37:12.586725\", \"2024-01-05T09:37:12.586725\", \"2024-01-18T09:37:12.586725\", \"2024-02-02T09:37:12.586725\", \"2024-02-05T09:37:12.586725\", \"2024-02-18T09:37:12.586725\"], \"maxstreak\": 6}",
    "{\"type\": \"YEARLY\", \"task\": \"Visit mum\", \"start\": \"2024-01-01\", \"finish\": \"2025-01-01\", \"periodicity\": [18, 2], \"trackData\": [\"2024-02-18T09:37:12.586725\"], \"maxstreak\": 1}",
    "{\"type\": \"YEARLY\", \"task\": \"Visit the dentist\", \"start\": \"2024-01-01\", \"finish\": \"2025-01-01\", \"periodicity\": [1, 1], \"trackData\": [\"2024-01-01T09:37:12.586725\"], \"maxstreak\": 1}"
]